kv/fs/__init__.py
kv/fs/__init__.pyi
kv/fs/api.py
kv/fs/append/__init__.py
kv/fs/append/append.py
kv/fs/append/ndjson.py
kv_fs-0.1.18.dist-info/METADATA
kv_fs-0.1.18.dist-info/WHEEL
kv_fs-0.1.18.dist-info/top_level.txt
kv_fs-0.1.18.dist-info/RECORD
