Metadata-Version: 2.1
Name: kv-fs
Version: 0.1.18
Summary: Key-Value DB API on the filesystem
Author-email: Marcel Claramunt <marcel@moveread.com>
Project-URL: repo, https://github.com/marciclabas/python-storage
Project-URL: home, https://github.com/marciclabas/python-storage/tree/main/kv/kv-fs
Requires-Python: >=3.10
Requires-Dist: kv-api
Requires-Dist: haskellian
Requires-Dist: lazy-loader
Requires-Dist: fs-tools
Requires-Dist: typing-extensions
